notebooklm/__init__.py
notebooklm/_artifacts.py
notebooklm/_chat.py
notebooklm/_core.py
notebooklm/_logging.py
notebooklm/_notebooks.py
notebooklm/_notes.py
notebooklm/_research.py
notebooklm/_settings.py
notebooklm/_sharing.py
notebooklm/_sources.py
notebooklm/_url_utils.py
notebooklm/auth.py
notebooklm/client.py
notebooklm/exceptions.py
notebooklm/notebooklm_cli.py
notebooklm/paths.py
notebooklm/types.py
notebooklm/cli/__init__.py
notebooklm/cli/artifact.py
notebooklm/cli/chat.py
notebooklm/cli/download.py
notebooklm/cli/download_helpers.py
notebooklm/cli/error_handler.py
notebooklm/cli/generate.py
notebooklm/cli/grouped.py
notebooklm/cli/helpers.py
notebooklm/cli/language.py
notebooklm/cli/note.py
notebooklm/cli/notebook.py
notebooklm/cli/options.py
notebooklm/cli/research.py
notebooklm/cli/session.py
notebooklm/cli/share.py
notebooklm/cli/skill.py
notebooklm/cli/source.py
notebooklm/data/SKILL.md
notebooklm/rpc/__init__.py
notebooklm/rpc/decoder.py
notebooklm/rpc/encoder.py
notebooklm/rpc/types.py
notebooklm_py-0.3.1.dist-info/METADATA
notebooklm_py-0.3.1.dist-info/WHEEL
notebooklm_py-0.3.1.dist-info/entry_points.txt
notebooklm_py-0.3.1.dist-info/licenses/LICENSE
notebooklm_py-0.3.1.dist-info/RECORD
