Metadata-Version: 2.4
Name: notebooklm-py
Version: 0.3.1
Summary: Unofficial Python library for automating Google NotebookLM
Project-URL: Homepage, https://github.com/teng-lin/notebooklm-py
Project-URL: Repository, https://github.com/teng-lin/notebooklm-py
Project-URL: Documentation, https://github.com/teng-lin/notebooklm-py#readme
Project-URL: Issues, https://github.com/teng-lin/notebooklm-py/issues
Author-email: Teng Lin <teng.lin@gmail.com>
License: MIT
License-File: LICENSE
Keywords: ai,api,automation,client,google,notebooklm,rpc
Classifier: Development Status :: 4 - Beta
Classifier: Intended Audience :: Developers
Classifier: License :: OSI Approved :: MIT License
Classifier: Programming Language :: Python :: 3
Classifier: Programming Language :: Python :: 3.10
Classifier: Programming Language :: Python :: 3.11
Classifier: Programming Language :: Python :: 3.12
Classifier: Programming Language :: Python :: 3.13
Classifier: Programming Language :: Python :: 3.14
Classifier: Topic :: Software Development :: Libraries :: Python Modules
Requires-Python: >=3.10
Requires-Dist: click>=8.0.0
Requires-Dist: httpx>=0.27.0
Requires-Dist: rich>=13.0.0
Provides-Extra: all
Requires-Dist: mypy>=1.0.0; extra == 'all'
Requires-Dist: playwright>=1.40.0; extra == 'all'
Requires-Dist: pytest-asyncio>=0.23.0; extra == 'all'
Requires-Dist: pytest-cov>=4.0.0; extra == 'all'
Requires-Dist: pytest-httpx>=0.30.0; extra == 'all'
Requires-Dist: pytest-rerunfailures>=14.0; extra == 'all'
Requires-Dist: pytest-timeout>=2.3.0; extra == 'all'
Requires-Dist: pytest>=8.0.0; extra == 'all'
Requires-Dist: python-dotenv>=1.0.0; extra == 'all'
Requires-Dist: ruff>=0.4.0; extra == 'all'
Requires-Dist: vcrpy>=6.0.0; extra == 'all'
Provides-Extra: browser
Requires-Dist: playwright>=1.40.0; extra == 'browser'
Provides-Extra: dev
Requires-Dist: mypy>=1.0.0; extra == 'dev'
Requires-Dist: pytest-asyncio>=0.23.0; extra == 'dev'
Requires-Dist: pytest-cov>=4.0.0; extra == 'dev'
Requires-Dist: pytest-httpx>=0.30.0; extra == 'dev'
Requires-Dist: pytest-rerunfailures>=14.0; extra == 'dev'
Requires-Dist: pytest-timeout>=2.3.0; extra == 'dev'
Requires-Dist: pytest>=8.0.0; extra == 'dev'
Requires-Dist: python-dotenv>=1.0.0; extra == 'dev'
Requires-Dist: ruff>=0.4.0; extra == 'dev'
Requires-Dist: vcrpy>=6.0.0; extra == 'dev'
